multi_swarm/__init__.py
multi_swarm/agency.py
multi_swarm/cli.py
multi_swarm/core/__init__.py
multi_swarm/core/agency.py
multi_swarm/core/agent.py
multi_swarm/core/base_agent.py
multi_swarm/core/config.py
multi_swarm/core/file.py
multi_swarm/core/flow.py
multi_swarm/core/interpreter.py
multi_swarm/core/rag.py
multi_swarm/core/thread.py
multi_swarm/core/thread_manager.py
multi_swarm/template/.cursorrules
multi_swarm/template/.env.example
multi_swarm/template/.gitignore
multi_swarm/template/.pre-commit-config.yaml
multi_swarm/template/LICENSE
multi_swarm/template/MANIFEST.in
multi_swarm/template/README.md
multi_swarm/template/RELEASE_NOTES.md
multi_swarm/template/__init__.py
multi_swarm/template/agency_manifesto.md
multi_swarm/template/mkdocs.yml
multi_swarm/template/pyproject.toml
multi_swarm/template/pytest.ini
multi_swarm/template/requirements.txt
multi_swarm/template/setup.cfg
multi_swarm/template/.github/CODE_OF_CONDUCT.md
multi_swarm/template/.github/CONTRIBUTING.md
multi_swarm/template/.github/pull_request_template.md
multi_swarm/template/.github/ISSUE_TEMPLATE/api_issue.md
multi_swarm/template/.github/ISSUE_TEMPLATE/bug_report.md
multi_swarm/template/.github/ISSUE_TEMPLATE/feature_request.md
multi_swarm/template/.github/workflows/ci.yml
multi_swarm/template/.github/workflows/publish.yml
multi_swarm/template/.github/workflows/test.yml
multi_swarm/template/docs/api-connections.md
multi_swarm/template/docs/index.md
multi_swarm/template/docs/llm-providers.md
multi_swarm/template/docs/v1.1.md
multi_swarm/template/docs/api/core.md
multi_swarm/template/docs/examples/dev-agency.md
multi_swarm/template/docs/getting-started/concepts.md
multi_swarm/template/docs/getting-started/installation.md
multi_swarm/template/docs/getting-started/quickstart.md
multi_swarm/template/docs/providers/claude.md
multi_swarm/template/docs/providers/gemini.md
multi_swarm/template/docs/user-guide/communication-flows.md
multi_swarm/template/docs/user-guide/creating-agencies.md
multi_swarm-1.0.3.dist-info/LICENSE
multi_swarm-1.0.3.dist-info/METADATA
multi_swarm-1.0.3.dist-info/WHEEL
multi_swarm-1.0.3.dist-info/entry_points.txt
multi_swarm-1.0.3.dist-info/top_level.txt
multi_swarm-1.0.3.dist-info/RECORD
