Metadata-Version: 2.2
Name: multi-swarm
Version: 1.0.3
Summary: A framework for creating collaborative AI agent swarms
Author-email: Bart Van Spitaels <bart.vanspitaels@gmail.com>
License: MIT
Project-URL: Documentation, https://github.com/bartvanspitaels99/multi-swarm/docs
Project-URL: Source, https://github.com/bartvanspitaels99/multi-swarm/
Project-URL: Issues, https://github.com/bartvanspitaels99/multi-swarm/issues
Keywords: ai,agents,llm,claude,gemini,multi-agent,rag,docker
Classifier: Development Status :: 5 - Production/Stable
Classifier: Intended Audience :: Developers
Classifier: License :: OSI Approved :: MIT License
Classifier: Operating System :: OS Independent
Classifier: Programming Language :: Python :: 3
Classifier: Programming Language :: Python :: 3.9
Classifier: Programming Language :: Python :: 3.10
Classifier: Programming Language :: Python :: 3.11
Classifier: Programming Language :: Python :: 3.12
Classifier: Topic :: Software Development :: Libraries :: Python Modules
Classifier: Topic :: Scientific/Engineering :: Artificial Intelligence
Requires-Python: >=3.8
License-File: LICENSE
Requires-Dist: anthropic>=0.18.1
Requires-Dist: google-generativeai>=0.3.2
Requires-Dist: pydantic>=2.0.0
Requires-Dist: python-dotenv>=1.0.0
Requires-Dist: docker>=6.1.0
Requires-Dist: sentence-transformers>=2.2.0
Requires-Dist: faiss-cpu>=1.7.4
Requires-Dist: transformers>=4.38.0
Requires-Dist: torch>=2.0.0
Requires-Dist: numpy>=1.24.0
Requires-Dist: click>=8.0.0
Provides-Extra: dev
Requires-Dist: pytest>=8.0.0; extra == "dev"
Requires-Dist: pytest-asyncio>=0.25.0; extra == "dev"
Requires-Dist: pytest-cov>=6.0.0; extra == "dev"
Requires-Dist: black>=24.0.0; extra == "dev"
Requires-Dist: isort>=5.0.0; extra == "dev"
Requires-Dist: mypy>=1.8.0; extra == "dev"
Provides-Extra: gpu
Requires-Dist: faiss-gpu>=1.7.4; extra == "gpu"
Requires-Dist: torch>=2.0.0; extra == "gpu"
